pluvo/__init__.py
pluvo/pluvo.py
pluvo-0.3.0.dist-info/LICENSE
pluvo-0.3.0.dist-info/METADATA
pluvo-0.3.0.dist-info/WHEEL
pluvo-0.3.0.dist-info/top_level.txt
pluvo-0.3.0.dist-info/RECORD
