Metadata-Version: 2.1
Name: pluvo
Version: 0.3.0
Summary: Python library to access the Pluvo REST API.
Home-page: https://github.com/wendbv/pluvo-python
Author: Wend BV
Author-email: info@wend.nl
License: MIT
Keywords: REST,API,Pluvo
Platform: UNKNOWN
Classifier: Development Status :: 4 - Beta
Classifier: Programming Language :: Python :: 2.7
Classifier: Programming Language :: Python :: 3.3
Classifier: Programming Language :: Python :: 3.4
Classifier: Programming Language :: Python :: 3.5
Classifier: Programming Language :: Python :: 3.6
License-File: LICENSE
Requires-Dist: requests
Provides-Extra: websocket
Requires-Dist: websockets ; extra == 'websocket'
